matproplib/__init__.py
matproplib/_version.py
matproplib/base.py
matproplib/conditions.py
matproplib/material.py
matproplib/nucleides.py
matproplib/superconduction.py
matproplib/converters/__init__.py
matproplib/converters/base.py
matproplib/converters/neutronics.py
matproplib/library/__init__.py
matproplib/library/beryllium.py
matproplib/library/concrete.py
matproplib/library/copper.py
matproplib/library/fluids.py
matproplib/library/lithium.py
matproplib/library/polymers.py
matproplib/library/references.py
matproplib/library/steel.py
matproplib/library/superconductors.py
matproplib/library/tungsten.py
matproplib/properties/__init__.py
matproplib/properties/dependent.py
matproplib/properties/group.py
matproplib/properties/independent.py
matproplib/properties/mixture.py
matproplib/tools/__init__.py
matproplib/tools/neutronics.py
matproplib/tools/plotting.py
matproplib/tools/serialisation.py
matproplib/tools/tools.py
matproplib-0.0.1.dist-info/METADATA
matproplib-0.0.1.dist-info/WHEEL
matproplib-0.0.1.dist-info/licenses/LICENSE
matproplib-0.0.1.dist-info/RECORD
